singer_target_iomete/__init__.py
singer_target_iomete/db_sync.py
singer_target_iomete/file_formats/__init__.py
singer_target_iomete/file_formats/csv_format.py
singer_target_iomete/utils/__init__.py
singer_target_iomete/utils/exceptions.py
singer_target_iomete/utils/flattening.py
singer_target_iomete/utils/s3_upload_client.py
singer_target_iomete/utils/stream_utils.py
singer_target_iomete-1.1.0.dist-info/LICENSE
singer_target_iomete-1.1.0.dist-info/METADATA
singer_target_iomete-1.1.0.dist-info/WHEEL
singer_target_iomete-1.1.0.dist-info/entry_points.txt
singer_target_iomete-1.1.0.dist-info/top_level.txt
singer_target_iomete-1.1.0.dist-info/RECORD
