Metadata-Version: 2.1
Name: singer-target-iomete
Version: 1.1.0
Summary: Singer.io target for loading data to iomete
Home-page: https://github.com/iomete
Author: Wise
Classifier: License :: OSI Approved :: Apache Software License
Classifier: Programming Language :: Python :: 3 :: Only
License-File: LICENSE
Requires-Dist: pipelinewise-singer-python (==1.*)
Requires-Dist: singer (==0.1.1)
Requires-Dist: inflection (==0.5.1)
Requires-Dist: joblib (==1.1.0)
Requires-Dist: boto3 (==1.20.20)
Requires-Dist: py-hive-iomete (==1.1.0)
Requires-Dist: pytest (==7.1.2)
Requires-Dist: python-dotenv (==0.21.0)
Provides-Extra: tests
Requires-Dist: pytest (==7.1.2) ; extra == 'tests'
Requires-Dist: pyspark (==3.2.1) ; extra == 'tests'
Requires-Dist: pyarrow (==9.0.0) ; extra == 'tests'
Requires-Dist: python-dotenv (==0.21.0) ; extra == 'tests'
